simple_math_package/__init__.py
simple_math_package/basic_operations.py
simple_math_package/intermediate_operations.py
simple_math_package-0.0.2.dist-info/METADATA
simple_math_package-0.0.2.dist-info/WHEEL
simple_math_package-0.0.2.dist-info/top_level.txt
simple_math_package-0.0.2.dist-info/RECORD
