Metadata-Version: 2.1
Name: simple-math-package
Version: 0.0.2
Summary: This package is used for simple math operations. It's used as an exercise to understand how to create and distribute a package.
Home-page: https://github.com/MatheusKomatsu/SimpleMathPackage
Author: matheus_eiji_faria_komatsu
Author-email: matheuskomatsu@hotmail.com
Requires-Python: >=3.8
